nameko_statsd/__init__.py
nameko_statsd/bases.py
nameko_statsd/statsd_dep.py
nameko_statsd-0.1.4.dist-info/LICENSE
nameko_statsd-0.1.4.dist-info/METADATA
nameko_statsd-0.1.4.dist-info/WHEEL
nameko_statsd-0.1.4.dist-info/top_level.txt
nameko_statsd-0.1.4.dist-info/zip-safe
nameko_statsd-0.1.4.dist-info/RECORD
