Metadata-Version: 2.1
Name: nameko-statsd
Version: 0.1.4
Summary: StatsD dependency for nameko services.
Home-page: https://github.com/sohonetlabs/nameko-statsd
Author: Sohonet product team
Author-email: fabrizio.romano@sohonet.com
License: MIT License
Platform: UNKNOWN
Classifier: Intended Audience :: Developers
Classifier: License :: OSI Approved :: MIT License
Classifier: Operating System :: MacOS :: MacOS X
Classifier: Operating System :: POSIX
Classifier: Programming Language :: Python
Classifier: Programming Language :: Python :: 3
Classifier: Programming Language :: Python :: 3.6
Classifier: Programming Language :: Python :: 3.7
Classifier: Programming Language :: Python :: 3.8
Classifier: Programming Language :: Python :: 3.9
Classifier: Topic :: Internet
Classifier: Topic :: Software Development :: Libraries :: Python Modules
Requires-Python: >=3.6
License-File: LICENSE
Requires-Dist: nameko (>=2.12)
Requires-Dist: statsd (>=3.2.1)
Requires-Dist: six (>=1.10.0)
Requires-Dist: mock (>=2.0.0)
Provides-Extra: dev
Requires-Dist: coverage ; extra == 'dev'
Requires-Dist: flake8 ; extra == 'dev'
Requires-Dist: pytest (<5.0.0) ; extra == 'dev'
Requires-Dist: restructuredtext-lint ; extra == 'dev'
Requires-Dist: Pygments ; extra == 'dev'
Requires-Dist: pytest-eventlet ; extra == 'dev'
